concatPDF/__init__.py
concatPDF/builder.py
concatPDF/make.py
concatPDF/quickstart.py
concatPDF/res/make.py
concatPDF-0.1.2.dist-info/DESCRIPTION.rst
concatPDF-0.1.2.dist-info/METADATA
concatPDF-0.1.2.dist-info/RECORD
concatPDF-0.1.2.dist-info/WHEEL
concatPDF-0.1.2.dist-info/entry_points.txt
concatPDF-0.1.2.dist-info/metadata.json
concatPDF-0.1.2.dist-info/top_level.txt
