Metadata-Version: 2.0
Name: concatPDF
Version: 0.1.2
Summary: Merge PDF files just like a build process.
Home-page: https://ritchievink.com
Author: Ritchie Vink
Author-email: UNKNOWN
License: MIT License
Download-URL: https://github.com/ritchie46/concatPDF
Requires-Dist: PyPDF2 (>=1.26.0)
